caissa.py
caissa-0.1.0.dist-info/LICENSE.txt
caissa-0.1.0.dist-info/METADATA
caissa-0.1.0.dist-info/RECORD
caissa-0.1.0.dist-info/WHEEL
caissa-0.1.0.dist-info/top_level.txt
